setup.py
effective/__init__.py
effective.egg-info/PKG-INFO
effective.egg-info/SOURCES.txt
effective.egg-info/dependency_links.txt
effective.egg-info/requires.txt
effective.egg-info/top_level.txt
effective/dataframe/__init__.py
effective/datetime/__init__.py
effective/env/__init__.py
effective/hive/__init__.py
effective/logger/__init__.py
effective/sql/__init__.py
effective/yaml/__init__.py