Metadata-Version: 1.0
Name: effective
Version: 0.1.41
Summary: A effective style to play in python
Home-page: https://github.com/GitHuHao/effective.git
Author: HuHao
Author-email: whohow20094702@163.com
License: GPL Licence
Keywords: pip,upsert,crud,mysql,sql,logging
Platform: any
